TuijianXitongYushangShenduXuexi150Fix1/README.md
TuijianXitongYushangShenduXuexi150Fix1/__init__.py
TuijianXitongYushangShenduXuexi150Fix1/__main__.py
TuijianXitongYushangShenduXuexi150Fix1/file.epub
TuijianXitongYushangShenduXuexi150Fix1/index.html
TuijianXitongYushangShenduXuexi150Fix1/css/__init__.py
TuijianXitongYushangShenduXuexi150Fix1/css/annotations.css
TuijianXitongYushangShenduXuexi150Fix1/css/main.css
TuijianXitongYushangShenduXuexi150Fix1/css/normalize.css
TuijianXitongYushangShenduXuexi150Fix1/css/popup.css
TuijianXitongYushangShenduXuexi150Fix1/font/__init__.py
TuijianXitongYushangShenduXuexi150Fix1/font/fontello.eot
TuijianXitongYushangShenduXuexi150Fix1/font/fontello.svg
TuijianXitongYushangShenduXuexi150Fix1/font/fontello.ttf
TuijianXitongYushangShenduXuexi150Fix1/font/fontello.woff
TuijianXitongYushangShenduXuexi150Fix1/img/__init__.py
TuijianXitongYushangShenduXuexi150Fix1/img/annotator-glyph-sprite.png
TuijianXitongYushangShenduXuexi150Fix1/img/annotator-icon-sprite.png
TuijianXitongYushangShenduXuexi150Fix1/img/apple-touch-icon.png
TuijianXitongYushangShenduXuexi150Fix1/img/cancelfullscreen.png
TuijianXitongYushangShenduXuexi150Fix1/img/close.png
TuijianXitongYushangShenduXuexi150Fix1/img/fullscreen.png
TuijianXitongYushangShenduXuexi150Fix1/img/loader.gif
TuijianXitongYushangShenduXuexi150Fix1/img/menu-icon.png
TuijianXitongYushangShenduXuexi150Fix1/img/save.png
TuijianXitongYushangShenduXuexi150Fix1/img/saved.png
TuijianXitongYushangShenduXuexi150Fix1/img/settings-s.png
TuijianXitongYushangShenduXuexi150Fix1/img/settings.png
TuijianXitongYushangShenduXuexi150Fix1/img/star.png
TuijianXitongYushangShenduXuexi150Fix1/js/__init__.py
TuijianXitongYushangShenduXuexi150Fix1/js/epub.js
TuijianXitongYushangShenduXuexi150Fix1/js/epub.min.js
TuijianXitongYushangShenduXuexi150Fix1/js/epub.min.map
TuijianXitongYushangShenduXuexi150Fix1/js/hooks.min.js
TuijianXitongYushangShenduXuexi150Fix1/js/hooks.min.map
tuijian_xitong_yushang_shendu_xuexi_1_50_fix1-2025.3.24.1.dist-info/METADATA
tuijian_xitong_yushang_shendu_xuexi_1_50_fix1-2025.3.24.1.dist-info/WHEEL
tuijian_xitong_yushang_shendu_xuexi_1_50_fix1-2025.3.24.1.dist-info/entry_points.txt
tuijian_xitong_yushang_shendu_xuexi_1_50_fix1-2025.3.24.1.dist-info/top_level.txt
tuijian_xitong_yushang_shendu_xuexi_1_50_fix1-2025.3.24.1.dist-info/RECORD
